django_routines/__init__.py
django_routines/apps.py
django_routines/exceptions.py
django_routines/signals.py
django_routines/management/__init__.py
django_routines/management/commands/__init__.py
django_routines/management/commands/routine.py
django_routines-1.6.2.dist-info/METADATA
django_routines-1.6.2.dist-info/WHEEL
django_routines-1.6.2.dist-info/licenses/LICENSE
django_routines-1.6.2.dist-info/RECORD
