Metadata-Version: 2.4
Name: django-routines
Version: 1.6.2
Summary: Define named groups of management commands in Django settings files for batched execution.
Project-URL: Homepage, https://django-routines.readthedocs.io
Project-URL: Documentation, https://django-routines.readthedocs.io
Project-URL: Repository, https://github.com/bckohan/django-routines
Project-URL: Issues, https://github.com/bckohan/django-routines/issues
Project-URL: Changelog, https://django-routines.readthedocs.io/en/latest/changelog.html
Project-URL: Code_of_Conduct, https://github.com/bckohan/django-routines/blob/main/CODE_OF_CONDUCT.md
Author-email: Brian Kohan <bckohan@gmail.com>
License-Expression: MIT
License-File: LICENSE
Keywords: CLI,backup,batch,commands,deploy,django,management,package,routine,routines,tasks
Classifier: Development Status :: 5 - Production/Stable
Classifier: Environment :: Console
Classifier: Framework :: Django
Classifier: Framework :: Django :: 3.2
Classifier: Framework :: Django :: 4.0
Classifier: Framework :: Django :: 4.1
Classifier: Framework :: Django :: 4.2
Classifier: Framework :: Django :: 5.0
Classifier: Framework :: Django :: 5.1
Classifier: Framework :: Django :: 5.2
Classifier: Framework :: Django :: 6.0
Classifier: Intended Audience :: Developers
Classifier: License :: OSI Approved :: MIT License
Classifier: Natural Language :: English
Classifier: Operating System :: OS Independent
Classifier: Programming Language :: Python
Classifier: Programming Language :: Python :: 3.9
Classifier: Programming Language :: Python :: 3.10
Classifier: Programming Language :: Python :: 3.11
Classifier: Programming Language :: Python :: 3.12
Classifier: Programming Language :: Python :: 3.13
Classifier: Programming Language :: Python :: 3.14
Classifier: Topic :: Internet :: WWW/HTTP
Classifier: Topic :: Internet :: WWW/HTTP :: Site Management
Classifier: Topic :: Software Development :: Libraries
Classifier: Topic :: Software Development :: Libraries :: Python Modules
Requires-Python: <4.0,>=3.9
Requires-Dist: django-typer<4.0,>=3.2.2
Requires-Dist: django<6.1,>=3.2
Provides-Extra: rich
Requires-Dist: rich<15.0.0,>=10.11.0; extra == 'rich'
